ashdisperse/__init__.py
ashdisperse/__main__.py
ashdisperse/ashdisperse.py
ashdisperse/queryreport.py
ashdisperse/version.py
ashdisperse/config/__init__.py
ashdisperse/config/config.py
ashdisperse/containers/__init__.py
ashdisperse/containers/cheb.py
ashdisperse/containers/velocities.py
ashdisperse/core/__init__.py
ashdisperse/core/core.py
ashdisperse/core/getters.py
ashdisperse/core/results.py
ashdisperse/data/GVP_Volcano_List.csv
ashdisperse/data/__init__.py
ashdisperse/data/era5.nc
ashdisperse/data/gvp_process.py
ashdisperse/data/metdata.npz
ashdisperse/interface/__init__.py
ashdisperse/interface/interface.py
ashdisperse/mapping/__init__.py
ashdisperse/mapping/epsg_defs.py
ashdisperse/mapping/mapping.py
ashdisperse/mapping/webmap.py
ashdisperse/met/__init__.py
ashdisperse/met/met.py
ashdisperse/met/met_adapters.py
ashdisperse/met/met_gfs.py
ashdisperse/met/met_netcdf.py
ashdisperse/met/repository.py
ashdisperse/notebooks/__init__.py
ashdisperse/notebooks/ashdisperse.ipynb
ashdisperse/notebooks/notebook_tools.py
ashdisperse/params/__init__.py
ashdisperse/params/emission_params.py
ashdisperse/params/grain_params.py
ashdisperse/params/met_params.py
ashdisperse/params/model_params.py
ashdisperse/params/output_params.py
ashdisperse/params/params.py
ashdisperse/params/physical_params.py
ashdisperse/params/solver_params.py
ashdisperse/params/source_params.py
ashdisperse/scripts/__init__.py
ashdisperse/scripts/clean.py
ashdisperse/scripts/run_ashdisperse_nb.py
ashdisperse/solver/__init__.py
ashdisperse/solver/solver.py
ashdisperse/solver/sources.py
ashdisperse/spectral/__init__.py
ashdisperse/spectral/cheb.py
ashdisperse/spectral/fourier.py
ashdisperse/utilities/__init__.py
ashdisperse/utilities/datetime_strings.py
ashdisperse/utilities/geo.py
ashdisperse/utilities/number_utils.py
ashdisperse/utilities/plotting.py
ashdisperse/utilities/utilities.py
ashdisperse-0.8.0.dist-info/licenses/LICENSE
ashdisperse-0.8.0.dist-info/METADATA
ashdisperse-0.8.0.dist-info/WHEEL
ashdisperse-0.8.0.dist-info/entry_points.txt
ashdisperse-0.8.0.dist-info/top_level.txt
ashdisperse-0.8.0.dist-info/RECORD
